{
    "id": 1478,
    "category": "Wine and bubbles",
    "sub category": "Ros\u00e9",
    "product": "Lancers Ros\u00e9 table wine",
    "price": 4.39,
    "unit": "0,75 lPrijs per LT \u20ac 5,85",
    "weight": "0.75 Liter",
    "calories": NaN,
    "ingredients": "Contains sulfites",
    "lifestyle": -1.0,
    "vegan": 1.0,
    "vegetarian": 1.0,
    "meat": -1.0,
    "sustainability": 0.0,
    "fraud probability": 0.32530120481927705,
    "price sensitivity": -0.757847533632287
}