{
    "id": 1247,
    "category": "Pasta, rice and world cuisine",
    "sub category": "Meal packs, mixes",
    "product": "AH Taco seasoning mix",
    "price": 0.85,
    "unit": "35 gPrijs per KG \u20ac 24,29",
    "weight": "35 Gram",
    "calories": 304.0,
    "ingredients": "Ingredi\u00ebnten: specerijen (paprikapoeder, ui, chilli pepper, knoflookpoeder, gemalen komijnzaden, gerookte paprikapoeder, jalapeno pepper powder, zwarte peper), 14% salt, dextrose, aardappelzetmeel, 1% gemalen oregano, voedingszuur (citroenzuur [E330]), kleurstof (paprika extract [160c])\nWaarvan toegevoegde suikers 13g per 100 gram en waarvan toegevoegd zout 14.30g per 100 gram",
    "lifestyle": 0.8,
    "vegan": 0.0,
    "vegetarian": 0.0,
    "meat": 0.0,
    "sustainability": 0.0,
    "fraud probability": 0.0,
    "price sensitivity": -0.9365079365079365
}