{
    "id": 2357,
    "category": "Breakfast cereals and spreads",
    "sub category": "Sweet spreads",
    "product": "Bolletje Schuddebuikjes speculaas",
    "price": 2.9,
    "unit": "300 gPrijs per KG \u20ac 6,97",
    "weight": "300 Gram",
    "calories": 478.0,
    "ingredients": "Ingredi\u00ebnten: TARWEBLOEM, suiker, plantaardige oli\u00ebn (palm, raap), plantaardige vezels, speculaaskruiden (bevat kaneel), glucose-fructosestroop, gekaramelliseerde suiker, rijsmiddelen (E500, E450), zout, sinaasappelschil, emulgator (zonnebloemlecithine). Kan sporen bevatten van andere glutenbevattende granen, pinda's en melk.",
    "lifestyle": -1.0,
    "vegan": 0.0,
    "vegetarian": 1.0,
    "meat": -1.0,
    "sustainability": 0.0,
    "fraud probability": 0.41698113207547166,
    "price sensitivity": -0.09677419354838723
}