{
    "id": 1772,
    "category": "Soft drinks, juices, coffee, tea",
    "sub category": "Tea",
    "product": "AH Zwarte thee earl grey",
    "price": 0.45,
    "unit": "20 stuks",
    "weight": "40 Gram",
    "calories": 1.0,
    "ingredients": "Ingredi\u00ebnten: 94% zwarte thee\u00b0, maltodextrine, aroma, 0,2% bergamotolie.\nWaarvan toegevoegde suikers 0.00g per 100 milliliter en waarvan toegevoegd zout 0.00g per 100 milliliter\n\u00b0Rainforest Alliance gecertificeerd. Zie voor meer informatie ra.org",
    "lifestyle": 1.0,
    "vegan": 1.0,
    "vegetarian": 1.0,
    "meat": -1.0,
    "sustainability": 0.0,
    "fraud probability": 0.0,
    "price sensitivity": -0.8439716312056738
}