{
    "id": 3149,
    "category": "Cheese, cold cuts, tapas",
    "sub category": "Cheese",
    "product": "De Zaanse Hoeve Jong belegen 48+ plakken",
    "price": 4.69,
    "unit": "400 gPrijs per KG \u20ac 11,73",
    "weight": "400 Gram",
    "calories": 355.0,
    "ingredients": "Ingredi\u00ebnten: melk*, zout, zuursel, vegetarisch stremsel.\nWaarvan toegevoegde suikers 0.00g per 100 gram en waarvan toegevoegd zout 1.90g per 100 gram\n*Van weidemelk.",
    "lifestyle": 0.2,
    "vegan": 0.0,
    "vegetarian": 1.0,
    "meat": -1.0,
    "sustainability": 0.0,
    "fraud probability": 0.44419391206313424,
    "price sensitivity": -0.012658227848101222
}