{
    "id": 3800,
    "category": "Potatoes, vegetables, fruit",
    "sub category": "Vegetables",
    "product": "AH Roerbakgroente Italiaans",
    "price": 2.29,
    "unit": "400 gPrijs per KG \u20ac 5,73",
    "weight": "400 Gram",
    "calories": 28.0,
    "ingredients": "Ingredi\u00ebnten: 27% prei, 18% wortel, 18% ui, 18% courgette, 18% rode paprika.\nWaarvan toegevoegde suikers 0.00g per 100 gram en waarvan toegevoegd zout 0.00g per 100 gram",
    "lifestyle": 1.0,
    "vegan": 1.0,
    "vegetarian": 1.0,
    "meat": -1.0,
    "sustainability": 0.0,
    "fraud probability": 0.3333333333333333,
    "price sensitivity": -0.1325301204819278
}